ArrayViewer/Charts.py
ArrayViewer/ClassAxes.py
ArrayViewer/Data.py
ArrayViewer/DataTree.py
ArrayViewer/Editor.py
ArrayViewer/LinePicker.py
ArrayViewer/Shape.py
ArrayViewer/Slider.py
ArrayViewer/Style.py
ArrayViewer/Viewer.py
ArrayViewer/__init__.py
ArrayViewer/burning.py
ArrayViewer/test.py
ArrayViewer/test2.py
ArrayViewer/test3.py
ArrayViewer/testFig.py
ArrayViewer-1.1.data/data/share/icons/aview_logo.svg
ArrayViewer-1.1.data/scripts/aview
ArrayViewer-1.1.dist-info/LICENSE
ArrayViewer-1.1.dist-info/METADATA
ArrayViewer-1.1.dist-info/WHEEL
ArrayViewer-1.1.dist-info/entry_points.txt
ArrayViewer-1.1.dist-info/top_level.txt
ArrayViewer-1.1.dist-info/RECORD
