Metadata-Version: 2.1
Name: ArrayViewer
Version: 1.1
Summary: ArrayViewer
Home-page: https://github.com/alexschw/ArrayViewer
Author: Alex Schwarz
Author-email: schwarz-alex@mail.de
License: GPLv3
Requires-Python: >=3.6
License-File: LICENSE
Requires-Dist: PyQt5
Requires-Dist: numpy
Requires-Dist: scipy
Requires-Dist: h5py
Requires-Dist: matplotlib
Requires-Dist: Pillow
Requires-Dist: natsort
